[
  {
    "decision_id": "respond-to-propaganda",
    "source_scenario_id": "ukraine-russia-conflict",
    "situation": "Russia is engaging in a propaganda campaign to manipulate public opinion about the conflict",
    "options": [
      {
        "id": "opt-a",
        "action": "Counter with factual information",
        "consequence": "Effective counter-narrative",
        "is_recommended": true
      },
      {
        "id": "opt-b",
        "action": "Ignore the propaganda",
        "consequence": "Propaganda goes unchallenged",
        "is_recommended": false
      }
    ],
    "recommended_action_id": "opt-a",
    "common_rookie_mistake": "Underestimating the impact of propaganda",
    "consequence_if_wrong": "Propaganda gains traction",
    "rationale": "Countering propaganda with factual information is essential to maintaining a accurate narrative and preventing the spread of misinformation",
    "_source_chunk_id": "zbirka-seminar-prava-liudyny-2023__ch001__ck001",
    "_source_slug": "zbirka-seminar-prava-liudyny-2023",
    "_chapter_title": "Висновки.",
    "_chapter_index": 1,
    "_chunk_index": 1,
    "_language": "uk",
    "_doc_type": "book"
  },
  {
    "decision_id": "manage-social-media-censorship",
    "source_scenario_id": "social-media-censorship",
    "situation": "Social media platforms are censoring content related to the conflict",
    "options": [
      {
        "id": "opt-c",
        "action": "Engage with social media platforms to understand their policies",
        "consequence": "Better understanding of censorship policies",
        "is_recommended": true
      },
      {
        "id": "opt-d",
        "action": "Publicly criticize social media platforms for censorship",
        "consequence": "Escalation of tensions with social media platforms",
        "is_recommended": false
      }
    ],
    "recommended_action_id": "opt-c",
    "common_rookie_mistake": "Overreacting to censorship",
    "consequence_if_wrong": "Damage to relationships with social media platforms",
    "rationale": "Engaging with social media platforms to understand their policies is essential to finding effective solutions to censorship",
    "_source_chunk_id": "zbirka-seminar-prava-liudyny-2023__ch001__ck001",
    "_source_slug": "zbirka-seminar-prava-liudyny-2023",
    "_chapter_title": "Висновки.",
    "_chapter_index": 1,
    "_chunk_index": 1,
    "_language": "uk",
    "_doc_type": "book"
  }
]