[
  {
    "scenario_id": "internally-displaced-persons-coverage",
    "crisis_type": "reputational",
    "severity": "medium",
    "context": "The Ukrainian media's coverage of internally displaced persons (IDPs) has been criticized for perpetuating negative stereotypes and hate speech. The media's portrayal of IDPs has contributed to their stigmatization and marginalization.",
    "key_stakeholders": [
      "IDPs",
      "Ukrainian media",
      "human rights organizations"
    ],
    "initial_trigger": "Negative media coverage of IDPs",
    "phase": "acute",
    "_source_chunk_id": "zbirka-seminar-prava-liudyny-2023__ch000__ck000",
    "_source_slug": "zbirka-seminar-prava-liudyny-2023",
    "_chapter_title": "Список використаних джерел",
    "_chapter_index": 0,
    "_chunk_index": 0,
    "_language": "uk",
    "_doc_type": "book"
  },
  {
    "scenario_id": "hate-speech-in-media",
    "crisis_type": "reputational",
    "severity": "high",
    "context": "The use of hate speech in the media can exacerbate social tensions and contribute to the marginalization of vulnerable groups, including IDPs.",
    "key_stakeholders": [
      "media outlets",
      "regulatory bodies",
      "human rights organizations"
    ],
    "initial_trigger": "Incident of hate speech in the media",
    "phase": "acute",
    "_source_chunk_id": "zbirka-seminar-prava-liudyny-2023__ch000__ck000",
    "_source_slug": "zbirka-seminar-prava-liudyny-2023",
    "_chapter_title": "Список використаних джерел",
    "_chapter_index": 0,
    "_chunk_index": 0,
    "_language": "uk",
    "_doc_type": "book"
  }
]